LICENSE.txt
README.rst
setup.cfg
setup.py
robprofile/__init__.py
robprofile/myprofile.py
robprofile.egg-info/PKG-INFO
robprofile.egg-info/SOURCES.txt
robprofile.egg-info/dependency_links.txt
robprofile.egg-info/top_level.txt